rave/__init__.py
rave/balancer.py
rave/blocks.py
rave/core.py
rave/dataset.py
rave/descript_discriminator.py
rave/discriminator.py
rave/model.py
rave/pqmf.py
rave/quantization.py
rave/resampler.py
rave/transforms.py
rave/version.py
rave/configs/adain.gin
rave/configs/causal.gin
rave/configs/descript_discriminator.gin
rave/configs/discrete.gin
rave/configs/discrete_v3.gin
rave/configs/hybrid.gin
rave/configs/noise.gin
rave/configs/normalize_ambient.gin
rave/configs/onnx.gin
rave/configs/raspberry.gin
rave/configs/snake.gin
rave/configs/spectral_discriminator.gin
rave/configs/spherical.gin
rave/configs/v1.gin
rave/configs/v2.gin
rave/configs/v2_nopqmf.gin
rave/configs/v2_nopqmf_small.gin
rave/configs/v2_small.gin
rave/configs/v2_with_augs.gin
rave/configs/v3.gin
rave/configs/wasserstein.gin
rave/configs/augmentations/compress.gin
rave/configs/augmentations/gain.gin
rave/configs/augmentations/mute.gin
rave/prior/__init__.py
rave/prior/core.py
rave/prior/model.py
rave/prior/residual_block.py
scripts/__init__.py
scripts/export.py
scripts/export_onnx.py
scripts/generate.py
scripts/main_cli.py
scripts/preprocess.py
scripts/remote_dataset.py
scripts/train.py
scripts/train_prior.py
tests/__init__.py
tests/test_configs.py
tests/test_resampler.py
tests/test_residual.py
acids_rave-2.3.1.dist-info/LICENSE
acids_rave-2.3.1.dist-info/METADATA
acids_rave-2.3.1.dist-info/WHEEL
acids_rave-2.3.1.dist-info/entry_points.txt
acids_rave-2.3.1.dist-info/top_level.txt
acids_rave-2.3.1.dist-info/RECORD
