Metadata-Version: 2.1
Name: acids-rave
Version: 2.3.1
Summary: RAVE: a Realtime Audio Variatione autoEncoder
Author: Antoine CAILLON
Author-email: caillon@ircam.fr
Classifier: Programming Language :: Python :: 3
Classifier: License :: OSI Approved :: MIT License
Classifier: Operating System :: OS Independent
Requires-Python: >=3.9
License-File: LICENSE
Requires-Dist: absl-py >=1.2.0
Requires-Dist: einops >=0.5.0
Requires-Dist: gin-config
Requires-Dist: GPUtil >=1.4.0
Requires-Dist: librosa >=0.9.2
Requires-Dist: numpy >=1.23.3
Requires-Dist: pytorch-lightning ==1.9.0
Requires-Dist: PyYAML >=6.0
Requires-Dist: scikit-learn >=1.1.2
Requires-Dist: scipy ==1.10.0
Requires-Dist: torch
Requires-Dist: tqdm >=4.64.1
Requires-Dist: udls >=1.0.1
Requires-Dist: cached-conv >=2.5.0
Requires-Dist: nn-tilde >=1.5.2
Requires-Dist: torchaudio
Requires-Dist: tensorboard
Requires-Dist: pytest >=7.2.2
Requires-Dist: Flask >=2.2.3
